{
  "telegram_id": 123456789,
  "type": "system",
  "ntf_type": "SUBSCRIPTION",
  "i18n_key": "ntf-event-subscription-new",
  "reply_markup_user_id": 123456789,
  "i18n_kwargs": {
    "payment_id": "b6f8f6b2-8b7e-4b0e-9e2b-6a2a2f7e0a04",
    "gateway_type": "YOOKASSA",
    "final_amount": "107.1",
    "discount_percent": 10,
    "original_amount": "119",
    "currency": "₽",
    "user_id": "123456789",
    "user_name": "John Doe",
    "username": "johndoe",
    "plan_name": "Pro",
    "plan_type": "BOTH",
    "plan_traffic_limit": 300,
    "plan_device_limit": 6,
    "plan_duration": 30
  }
}
